{"openapi":"3.0.1","info":{"title":"Bygglet API","description":"Welcome to our API. <br> <h3> Customer </h3> <ul>\n  <li>Information regarding the Customer Domain Object and its mapping towards the database can be found <a href=\"https://docs.google.com/spreadsheets/d/1x5L0XiQZYUmfZBwYJWQ-mTtfzVKl4RZbmGJGtNrbedw/edit?usp=sharing\">here</a>.</li></ul>","version":"v1"},"servers":[{"url":"http://localhost:8080","description":"Generated server url"}],"paths":{"/customers/{customerId}":{"get":{"tags":["Customers"],"operationId":"getOne","parameters":[{"name":"customerId","in":"path","required":true,"schema":{"type":"integer","format":"int64"}},{"name":"company-id","in":"header","required":true,"schema":{"type":"integer","format":"int64"}}],"responses":{"400":{"description":"Bad Request","content":{"*/*":{"schema":{"oneOf":[{"type":"object","additionalProperties":{"type":"string"}},{"type":"string"}]}}}},"404":{"description":"Not Found","content":{"*/*":{"schema":{"type":"string"}}}},"200":{"description":"OK","content":{"*/*":{"schema":{"$ref":"#/components/schemas/ResponseModelCustomer"}}}}}},"put":{"tags":["Customers"],"operationId":"put","parameters":[{"name":"customerId","in":"path","required":true,"schema":{"type":"integer","format":"int64"}},{"name":"company-id","in":"header","required":true,"schema":{"type":"integer","format":"int64"}}],"requestBody":{"content":{"application/json":{"schema":{"$ref":"#/components/schemas/Customer"}}},"required":true},"responses":{"400":{"description":"Bad Request","content":{"*/*":{"schema":{"oneOf":[{"type":"object","additionalProperties":{"type":"string"}},{"type":"string"}]}}}},"404":{"description":"Not Found","content":{"*/*":{"schema":{"type":"string"}}}},"200":{"description":"OK","content":{"*/*":{"schema":{"$ref":"#/components/schemas/ResponseModelCustomer"}}}}}},"delete":{"tags":["Customers"],"operationId":"delete","parameters":[{"name":"customerId","in":"path","required":true,"schema":{"type":"integer","format":"int64"}},{"name":"company-id","in":"header","required":true,"schema":{"type":"integer","format":"int64"}}],"responses":{"400":{"description":"Bad Request","content":{"*/*":{"schema":{"oneOf":[{"type":"object","additionalProperties":{"type":"string"}},{"type":"string"}]}}}},"404":{"description":"Not Found","content":{"*/*":{"schema":{"type":"string"}}}},"204":{"description":"No Content"}}}},"/customers/{customerId}/markups":{"get":{"tags":["CustomerMarkups"],"operationId":"getAll_1","parameters":[{"name":"customerId","in":"path","required":true,"schema":{"type":"integer","format":"int64"}},{"name":"company-id","in":"header","required":true,"schema":{"type":"integer","format":"int64"}}],"responses":{"400":{"description":"Bad Request","content":{"*/*":{"schema":{"oneOf":[{"type":"object","additionalProperties":{"type":"string"}},{"type":"string"}]}}}},"404":{"description":"Not Found","content":{"*/*":{"schema":{"type":"string"}}}},"200":{"description":"OK","content":{"*/*":{"schema":{"$ref":"#/components/schemas/ResponseModelMarkups"}}}}}},"put":{"tags":["CustomerMarkups"],"operationId":"update","parameters":[{"name":"customerId","in":"path","required":true,"schema":{"type":"integer","format":"int64"}},{"name":"company-id","in":"header","required":true,"schema":{"type":"integer","format":"int64"}}],"requestBody":{"content":{"application/json":{"schema":{"$ref":"#/components/schemas/Markups"}}},"required":true},"responses":{"400":{"description":"Bad Request","content":{"*/*":{"schema":{"oneOf":[{"type":"object","additionalProperties":{"type":"string"}},{"type":"string"}]}}}},"404":{"description":"Not Found","content":{"*/*":{"schema":{"type":"string"}}}},"200":{"description":"OK","content":{"application/json":{"schema":{"$ref":"#/components/schemas/ResponseModelMarkups"}}}}}},"post":{"tags":["CustomerMarkups"],"operationId":"create","parameters":[{"name":"customerId","in":"path","required":true,"schema":{"type":"integer","format":"int64"}},{"name":"company-id","in":"header","required":true,"schema":{"type":"integer","format":"int64"}}],"requestBody":{"content":{"application/json":{"schema":{"$ref":"#/components/schemas/Markups"}}},"required":true},"responses":{"400":{"description":"Bad Request","content":{"*/*":{"schema":{"oneOf":[{"type":"object","additionalProperties":{"type":"string"}},{"type":"string"}]}}}},"404":{"description":"Not Found","content":{"*/*":{"schema":{"type":"string"}}}},"201":{"description":"Created","content":{"application/json":{"schema":{"$ref":"#/components/schemas/ResponseModelMarkups"}}}}}}},"/customers/{customerId}/extensions/{extensionKey}":{"put":{"tags":["CustomerExtensions"],"operationId":"update_1","parameters":[{"name":"customerId","in":"path","required":true,"schema":{"type":"integer","format":"int64"}},{"name":"extensionKey","in":"path","required":true,"schema":{"type":"string","enum":["INVOICE_EMAIL","INVOICE_REMINDER_EMAIL","EDI_ROUTE","E_INVOICE_ADDRESS","CAN_RECEIVE_EHF_3","PAYEX_NEW_EDI_ROUTE","PAYEX_RECEIVE_INVOICE_SERVICE_ORDER_BY_EMAIL","PAYEX_DISABLE_FACTORING"]}},{"name":"company-id","in":"header","required":true,"schema":{"type":"integer","format":"int64"}}],"requestBody":{"content":{"application/json":{"schema":{"$ref":"#/components/schemas/Value"}}},"required":true},"responses":{"400":{"description":"Bad Request","content":{"*/*":{"schema":{"oneOf":[{"type":"object","additionalProperties":{"type":"string"}},{"type":"string"}]}}}},"404":{"description":"Not Found","content":{"*/*":{"schema":{"type":"string"}}}},"200":{"description":"OK","content":{"application/json":{"schema":{"$ref":"#/components/schemas/ResponseModelCustomerExtensions"}}}}}},"delete":{"tags":["CustomerExtensions"],"operationId":"delete_2","parameters":[{"name":"customerId","in":"path","required":true,"schema":{"type":"integer","format":"int64"}},{"name":"extensionKey","in":"path","required":true,"schema":{"type":"string","enum":["INVOICE_EMAIL","INVOICE_REMINDER_EMAIL","EDI_ROUTE","E_INVOICE_ADDRESS","CAN_RECEIVE_EHF_3","PAYEX_NEW_EDI_ROUTE","PAYEX_RECEIVE_INVOICE_SERVICE_ORDER_BY_EMAIL","PAYEX_DISABLE_FACTORING"]}},{"name":"company-id","in":"header","required":true,"schema":{"type":"integer","format":"int64"}}],"responses":{"400":{"description":"Bad Request","content":{"*/*":{"schema":{"oneOf":[{"type":"object","additionalProperties":{"type":"string"}},{"type":"string"}]}}}},"404":{"description":"Not Found","content":{"*/*":{"schema":{"type":"string"}}}},"204":{"description":"No Content"}}}},"/customers/{customerId}/contacts/{contactId}":{"get":{"tags":["CustomerContacts"],"operationId":"getOne_1","parameters":[{"name":"customerId","in":"path","required":true,"schema":{"type":"integer","format":"int64"}},{"name":"contactId","in":"path","required":true,"schema":{"type":"integer","format":"int64"}},{"name":"company-id","in":"header","required":true,"schema":{"type":"integer","format":"int64"}}],"responses":{"400":{"description":"Bad Request","content":{"*/*":{"schema":{"oneOf":[{"type":"object","additionalProperties":{"type":"string"}},{"type":"string"}]}}}},"404":{"description":"Not Found","content":{"*/*":{"schema":{"type":"string"}}}},"200":{"description":"OK","content":{"*/*":{"schema":{"$ref":"#/components/schemas/ResponseModelContact"}}}}}},"put":{"tags":["CustomerContacts"],"operationId":"update_2","parameters":[{"name":"customerId","in":"path","required":true,"schema":{"type":"integer","format":"int64"}},{"name":"contactId","in":"path","required":true,"schema":{"type":"integer","format":"int64"}},{"name":"company-id","in":"header","required":true,"schema":{"type":"integer","format":"int64"}}],"requestBody":{"content":{"application/json":{"schema":{"$ref":"#/components/schemas/Contact"}}},"required":true},"responses":{"400":{"description":"Bad Request","content":{"*/*":{"schema":{"oneOf":[{"type":"object","additionalProperties":{"type":"string"}},{"type":"string"}]}}}},"404":{"description":"Not Found","content":{"*/*":{"schema":{"type":"string"}}}},"200":{"description":"OK","content":{"application/json":{"schema":{"$ref":"#/components/schemas/ResponseModelContact"}}}}}},"delete":{"tags":["CustomerContacts"],"operationId":"delete_3","parameters":[{"name":"customerId","in":"path","required":true,"schema":{"type":"integer","format":"int64"}},{"name":"contactId","in":"path","required":true,"schema":{"type":"integer","format":"int64"}},{"name":"company-id","in":"header","required":true,"schema":{"type":"integer","format":"int64"}}],"responses":{"400":{"description":"Bad Request","content":{"*/*":{"schema":{"oneOf":[{"type":"object","additionalProperties":{"type":"string"}},{"type":"string"}]}}}},"404":{"description":"Not Found","content":{"*/*":{"schema":{"type":"string"}}}},"204":{"description":"No Content"}}}},"/customers":{"get":{"tags":["Customers"],"operationId":"getAll","parameters":[{"name":"company-id","in":"header","required":true,"schema":{"type":"string"}},{"name":"filter","in":"query","required":true,"schema":{"$ref":"#/components/schemas/CustomerFilter"}},{"name":"pageable","in":"query","required":true,"schema":{"$ref":"#/components/schemas/Pageable"}}],"responses":{"400":{"description":"Bad Request","content":{"*/*":{"schema":{"oneOf":[{"type":"object","additionalProperties":{"type":"string"}},{"type":"string"}]}}}},"404":{"description":"Not Found","content":{"*/*":{"schema":{"type":"string"}}}},"200":{"description":"OK","content":{"*/*":{"schema":{"$ref":"#/components/schemas/DomainPageResponseModelCustomerBase"}}}}}},"post":{"tags":["Customers"],"operationId":"post","parameters":[{"name":"company-id","in":"header","required":true,"schema":{"type":"integer","format":"int64"}}],"requestBody":{"content":{"application/json":{"schema":{"$ref":"#/components/schemas/Customer"}}},"required":true},"responses":{"400":{"description":"Bad Request","content":{"*/*":{"schema":{"oneOf":[{"type":"object","additionalProperties":{"type":"string"}},{"type":"string"}]}}}},"404":{"description":"Not Found","content":{"*/*":{"schema":{"type":"string"}}}},"201":{"description":"Created","content":{"application/json":{"schema":{"$ref":"#/components/schemas/ResponseModelCustomer"}}}}}}},"/customers/{customerId}/contacts":{"get":{"tags":["CustomerContacts"],"operationId":"getAll_3","parameters":[{"name":"customerId","in":"path","required":true,"schema":{"type":"integer","format":"int64"}},{"name":"company-id","in":"header","required":true,"schema":{"type":"integer","format":"int64"}}],"responses":{"400":{"description":"Bad Request","content":{"*/*":{"schema":{"oneOf":[{"type":"object","additionalProperties":{"type":"string"}},{"type":"string"}]}}}},"404":{"description":"Not Found","content":{"*/*":{"schema":{"type":"string"}}}},"200":{"description":"OK","content":{"*/*":{"schema":{"$ref":"#/components/schemas/ResponseModelContacts"}}}}}},"post":{"tags":["CustomerContacts"],"operationId":"create_1","parameters":[{"name":"customerId","in":"path","required":true,"schema":{"type":"integer","format":"int64"}},{"name":"company-id","in":"header","required":true,"schema":{"type":"integer","format":"int64"}}],"requestBody":{"content":{"application/json":{"schema":{"$ref":"#/components/schemas/Contact"}}},"required":true},"responses":{"400":{"description":"Bad Request","content":{"*/*":{"schema":{"oneOf":[{"type":"object","additionalProperties":{"type":"string"}},{"type":"string"}]}}}},"404":{"description":"Not Found","content":{"*/*":{"schema":{"type":"string"}}}},"201":{"description":"Created","content":{"application/json":{"schema":{"$ref":"#/components/schemas/ResponseModelContact"}}}}}}},"/customers/{customerId}/extensions":{"get":{"tags":["CustomerExtensions"],"operationId":"getAll_2","parameters":[{"name":"customerId","in":"path","required":true,"schema":{"type":"integer","format":"int64"}},{"name":"company-id","in":"header","required":true,"schema":{"type":"integer","format":"int64"}}],"responses":{"400":{"description":"Bad Request","content":{"*/*":{"schema":{"oneOf":[{"type":"object","additionalProperties":{"type":"string"}},{"type":"string"}]}}}},"404":{"description":"Not Found","content":{"*/*":{"schema":{"type":"string"}}}},"200":{"description":"OK","content":{"*/*":{"schema":{"$ref":"#/components/schemas/ResponseModelMarkups"}}}}}}},"/":{"get":{"tags":["health-controller"],"operationId":"healthCheck","responses":{"400":{"description":"Bad Request","content":{"*/*":{"schema":{"oneOf":[{"type":"object","additionalProperties":{"type":"string"}},{"type":"string"}]}}}},"404":{"description":"Not Found","content":{"*/*":{"schema":{"type":"string"}}}},"200":{"description":"OK","content":{"*/*":{"schema":{"type":"string"}}}}}}},"/customers/{customerId}/markups/{markupId}":{"delete":{"tags":["CustomerMarkups"],"operationId":"delete_1","parameters":[{"name":"customerId","in":"path","required":true,"schema":{"type":"integer","format":"int64"}},{"name":"markupId","in":"path","required":true,"schema":{"type":"integer","format":"int64"}},{"name":"company-id","in":"header","required":true,"schema":{"type":"integer","format":"int64"}}],"responses":{"400":{"description":"Bad Request","content":{"*/*":{"schema":{"oneOf":[{"type":"object","additionalProperties":{"type":"string"}},{"type":"string"}]}}}},"404":{"description":"Not Found","content":{"*/*":{"schema":{"type":"string"}}}},"204":{"description":"No Content"}}}}},"components":{"schemas":{"Address":{"type":"object","properties":{"countryCode":{"maxLength":2,"minLength":2,"type":"string","example":"SE","default":"SE","enum":["DK, FI, NO, SE"]},"city":{"maxLength":255,"minLength":0,"type":"string","nullable":true,"example":"Gothenburg","default":"null"},"longitude":{"type":"number","format":"double","example":57.72599599867971,"default":0.0},"latitude":{"type":"number","format":"double","example":12.016378445749266,"default":0.0},"street":{"maxLength":255,"minLength":0,"type":"string","example":"von Utfallsgatan 1"},"zip":{"type":"integer","format":"int32","example":41505,"default":0}}},"Customer":{"required":["name"],"type":"object","properties":{"id":{"type":"integer","format":"int64","readOnly":true},"referenceNumber":{"maxLength":45,"minLength":0,"type":"string","description":"Customer reference, usually a customer number","nullable":true,"example":"C9152","default":"null"},"name":{"maxLength":255,"minLength":1,"type":"string","description":"Name of the customer, both first name and last name if Type is PRIVATE_PERSON","example":"Bygglet AB"},"active":{"type":"boolean","example":true,"default":true},"identification":{"maxLength":45,"minLength":0,"type":"string","description":"A unique identifier such as organization number if Type is COMPANY, or if Type is PRIVATE_PERSON it can be a SSN.","nullable":true,"example":"556822-0635","default":"null"},"type":{"type":"string","example":"COMPANY","default":"COMPANY","enum":["COMPANY","PRIVATE_PERSON","COMPANY, PRIVATE_PERSON"]},"vatNumber":{"maxLength":45,"minLength":0,"type":"string","nullable":true,"example":"SE556822063501","default":"null"},"articlePriceListId":{"type":"integer","description":"Identifier of an existing and active article price list that will be connected to the customer.","format":"int64","nullable":true,"example":1000},"email":{"type":"string","nullable":true,"example":"info@bygglet.com","default":"null"},"gln":{"maxLength":45,"minLength":0,"type":"string","description":"GLN is an identifier and is used to identify delivery and billing addresses.","nullable":true,"example":"7369165551785","default":"null"},"invoiceSettings":{"$ref":"#/components/schemas/CustomerInvoiceSettings"},"mailingAddress":{"$ref":"#/components/schemas/Address"},"note":{"maxLength":255,"minLength":0,"type":"string","description":"Internal note on the customer.","nullable":true,"example":"The current invoice should be sent on the 25th electronically. / Back Office","default":"null"},"primaryPhoneNumber":{"maxLength":45,"minLength":0,"type":"string","nullable":true,"example":"+46731231231","default":"null"},"secondaryPhoneNumber":{"maxLength":45,"minLength":0,"type":"string","nullable":true,"example":"031-144205","default":"null"},"settings":{"$ref":"#/components/schemas/CustomerSettingsHolder"},"visitingAddress":{"$ref":"#/components/schemas/Address"},"website":{"maxLength":255,"minLength":0,"type":"string","nullable":true,"example":"https://www.bygglet.com","default":"null"}}},"CustomerInvoiceSettings":{"type":"object","properties":{"address":{"$ref":"#/components/schemas/Address"},"email":{"type":"string","nullable":true,"example":"invoice@bygglet.com","default":"null"},"reminderEmail":{"type":"string","nullable":true,"example":"contact@bygglet.com","default":"null"},"paymentTerms":{"type":"integer","format":"int32","example":30,"default":30},"reversedVat":{"type":"boolean","example":false,"default":false},"hourlyRate":{"type":"number","format":"double","example":650,"default":0.0},"vendorInvoiceSurchargePercentage":{"maximum":100,"minimum":-100,"type":"number","description":"Percentage to be surcharged on vendor invoices. 12 in this case will be 12%","format":"double","example":12,"default":0.0},"sendMethod":{"type":"string","description":"The standard way of sending invoices to the customer.","example":"EMAIL","default":"EMAIL","enum":["EMAIL","MAIL","E_INVOICE","BYGGLET_INTERNAL","UNKNOWN"]}}},"CustomerSettingsHolder":{"type":"object","properties":{"showVatOnTender":{"type":"boolean","description":"Whether or not VAT should be presented explicitly on tenders.","example":true,"default":false}}},"Href":{"type":"object","properties":{"href":{"type":"string"}}},"Meta":{"type":"object","properties":{"links":{"type":"object","additionalProperties":{"$ref":"#/components/schemas/Href"}}}},"ResponseModelCustomer":{"type":"object","properties":{"data":{"$ref":"#/components/schemas/Customer"},"meta":{"$ref":"#/components/schemas/Meta"}}},"Markup":{"required":["name"],"type":"object","properties":{"id":{"type":"integer","format":"int64"},"name":{"type":"string","example":"Projektnummer"},"required":{"type":"boolean"}}},"Markups":{"required":["markups"],"type":"object","properties":{"markups":{"maxItems":20,"minItems":1,"type":"array","items":{"$ref":"#/components/schemas/Markup"}}}},"ResponseModelMarkups":{"type":"object","properties":{"data":{"$ref":"#/components/schemas/Markups"},"meta":{"$ref":"#/components/schemas/Meta"}}},"Value":{"required":["value"],"type":"object","properties":{"value":{"type":"string","example":"MY_E_INVOICE_ADDRESS"}}},"CustomerExtensions":{"required":["value"],"type":"object","properties":{"key":{"type":"string","example":"INVOICE_E_INVOICE_ADDRESS","enum":["INVOICE_EMAIL","INVOICE_REMINDER_EMAIL","EDI_ROUTE","E_INVOICE_ADDRESS","CAN_RECEIVE_EHF_3","PAYEX_NEW_EDI_ROUTE","PAYEX_RECEIVE_INVOICE_SERVICE_ORDER_BY_EMAIL","PAYEX_DISABLE_FACTORING"]},"value":{"type":"string"}}},"ResponseModelCustomerExtensions":{"type":"object","properties":{"data":{"$ref":"#/components/schemas/CustomerExtensions"},"meta":{"$ref":"#/components/schemas/Meta"}}},"Contact":{"required":["firstName","lastName"],"type":"object","properties":{"id":{"type":"integer","format":"int64"},"firstName":{"maxLength":128,"minLength":1,"type":"string","example":"Sven"},"lastName":{"maxLength":128,"minLength":0,"type":"string","example":"Svensson"},"address":{"$ref":"#/components/schemas/Address"},"number":{"type":"string"},"socialSecurityNumber":{"type":"string"},"primaryPhoneNumber":{"type":"string"},"secondaryPhoneNumber":{"type":"string"},"email":{"type":"string"},"note":{"type":"string"},"active":{"type":"boolean"}}},"ResponseModelContact":{"type":"object","properties":{"data":{"$ref":"#/components/schemas/Contact"},"meta":{"$ref":"#/components/schemas/Meta"}}},"CustomerFilter":{"type":"object","properties":{"customerName":{"type":"string"},"active":{"type":"boolean"}}},"Pageable":{"type":"object","properties":{"page":{"minimum":0,"type":"integer","format":"int32"},"size":{"minimum":1,"type":"integer","format":"int32"},"sort":{"type":"array","items":{"type":"string"}}}},"CustomerBase":{"required":["name"],"type":"object","properties":{"id":{"type":"integer","format":"int64","readOnly":true},"referenceNumber":{"maxLength":45,"minLength":0,"type":"string","description":"Customer reference, usually a customer number","nullable":true,"example":"C9152","default":"null"},"name":{"maxLength":255,"minLength":1,"type":"string","description":"Name of the customer, both first name and last name if Type is PRIVATE_PERSON","example":"Bygglet AB"},"active":{"type":"boolean","example":true,"default":true},"identification":{"maxLength":45,"minLength":0,"type":"string","description":"A unique identifier such as organization number if Type is COMPANY, or if Type is PRIVATE_PERSON it can be a SSN.","nullable":true,"example":"556822-0635","default":"null"},"type":{"type":"string","example":"COMPANY","default":"COMPANY","enum":["COMPANY","PRIVATE_PERSON","COMPANY, PRIVATE_PERSON"]},"vatNumber":{"maxLength":45,"minLength":0,"type":"string","nullable":true,"example":"SE556822063501","default":"null"}}},"DomainPageResponseModelCustomerBase":{"type":"object","properties":{"content":{"type":"array","items":{"$ref":"#/components/schemas/ResponseModelCustomerBase"}},"totalElements":{"type":"integer","format":"int64"},"page":{"type":"integer","format":"int32"},"size":{"type":"integer","format":"int32"}}},"ResponseModelCustomerBase":{"type":"object","properties":{"data":{"$ref":"#/components/schemas/CustomerBase"},"meta":{"$ref":"#/components/schemas/Meta"}}},"Contacts":{"type":"object","properties":{"contacts":{"type":"array","items":{"$ref":"#/components/schemas/Contact"}}}},"ResponseModelContacts":{"type":"object","properties":{"data":{"$ref":"#/components/schemas/Contacts"},"meta":{"$ref":"#/components/schemas/Meta"}}}}}}
